Metadata-Version: 1.1
Name: altify
Version: 4.0
Summary: Uses deep learning to caption img tags within a web page and fills out their alt attribute with the related caption
Home-page: https://github.com/parhamp/altify
Author: Parham Pourdavood
Author-email: ppourdavood@gmail.com
License: Apache-2.0
Download-URL: https://github.com/parhamp/altify/tarball/3.3
Keywords: alt,caption,images,deep learning
Platform: UNKNOWN
